{"chunk_definitions":[{"row":10,"row_count":1,"visible":true,"expansion_state":0,"options":{"engine":"r","label":"setup","include":false,"echo":false,"dev":"png"},"document_id":"28F14193","chunk_id":"ctylwvccl3rhd","chunk_label":"unnamed-chunk-1"},{"row":16,"row_count":1,"visible":true,"expansion_state":0,"options":{"engine":"r","filename":"purrr関数のロード","label":"unnamed-chunk-2","dev":"png"},"document_id":"B63D7EAA","chunk_id":"ctbzohq44pzwp","chunk_label":"unnamed-chunk-2"},{"row":30,"row_count":1,"visible":true,"expansion_state":0,"options":{"engine":"r","filename":"ベクターを引数とするmap関数","label":"unnamed-chunk-3","dev":"png"},"document_id":"B63D7EAA","chunk_id":"cothsmmvibg5x","chunk_label":"unnamed-chunk-3"},{"row":41,"row_count":1,"visible":true,"expansion_state":0,"options":{"engine":"r","filename":"リストを引数とするmap関数","label":"unnamed-chunk-4","dev":"png"},"document_id":"B63D7EAA","chunk_id":"cxy9fur5h8p3f","chunk_label":"unnamed-chunk-4"}],"doc_write_time":1742085350}